start_url/__init__.py
start_url/headers.py
start_url/main.py
start_url/meta.py
start_url/url.py
start_url-0.0.8.dist-info/METADATA
start_url-0.0.8.dist-info/WHEEL
start_url-0.0.8.dist-info/RECORD
